europemapper/__init__.py
europemapper/europemapper.py
europemapper-0.0.2.dist-info/LICENSE
europemapper-0.0.2.dist-info/METADATA
europemapper-0.0.2.dist-info/WHEEL
europemapper-0.0.2.dist-info/top_level.txt
europemapper-0.0.2.dist-info/RECORD
